COPYING
CREDITS
MANIFEST.in
README.rst
setup.py
yolk/__init__.py
yolk/__main__.py
yolk/cli.py
yolk/metadata.py
yolk/pypi.py
yolk/setuptools_support.py
yolk/utils.py
yolk/yolklib.py
yolk3k.egg-info/PKG-INFO
yolk3k.egg-info/SOURCES.txt
yolk3k.egg-info/dependency_links.txt
yolk3k.egg-info/entry_points.txt
yolk3k.egg-info/top_level.txt