Metadata-Version: 1.1
Name: yolk3k
Version: 0.8
Summary: Command-line tool for querying PyPI and Python packages installed on your system.
Home-page: https://github.com/myint/yolk
Author: Steven Myint
Author-email: UNKNOWN
License: BSD License
Keywords: PyPI,setuptools,cheeseshop,distutils,eggs,package,management
Platform: UNKNOWN
Classifier: Development Status :: 5 - Production/Stable
Classifier: Intended Audience :: Developers
Classifier: License :: OSI Approved :: BSD License
Classifier: Programming Language :: Python
Classifier: Programming Language :: Python :: 2
Classifier: Programming Language :: Python :: 2.7
Classifier: Programming Language :: Python :: 3
Classifier: Programming Language :: Python :: 3.2
Classifier: Programming Language :: Python :: 3.3
Classifier: Programming Language :: Python :: 3.4
Classifier: Topic :: Software Development :: Libraries :: Python Modules
